[
    {
        "name": "Alice Johnson",
        "age": 25,
        "email": "alice.johnson@example.com",
        "jobTitle": "Software Developer",
        "experience": "3 years"
    },
    {
        "name": "Bob Smith",
        "age": 30,
        "email": "bob.smith@example.com",
        "jobTitle": "Data Analyst",
        "experience": "5 years"
    },
    {
        "name": "Charlie Brown",
        "age": 28,
        "email": "charlie.brown@example.com",
        "jobTitle": "Project Manager",
        "experience": "6 years"
    },
    {
        "name": "Diana Adams",
        "age": 32,
        "email": "diana.adams@example.com",
        "jobTitle": "UX Designer",
        "experience": "7 years"
    },
    {
        "name": "Ethan Wright",
        "age": 24,
        "email": "ethan.wright@example.com",
        "jobTitle": "Front-End Developer",
        "experience": "2 years"
    },
    {
        "name": "Fiona Green",
        "age": 29,
        "email": "fiona.green@example.com",
        "jobTitle": "HR Specialist",
        "experience": "5 years"
    },
    {
        "name": "George Wilson",
        "age": 35,
        "email": "george.wilson@example.com",
        "jobTitle": "DevOps Engineer",
        "experience": "8 years"
    },
    {
        "name": "Hannah Lee",
        "age": 27,
        "email": "hannah.lee@example.com",
        "jobTitle": "Digital Marketer",
        "experience": "4 years"
    },
    {
        "name": "Ian Clarke",
        "age": 31,
        "email": "ian.clarke@example.com",
        "jobTitle": "Full-Stack Developer",
        "experience": "6 years"
    },
    {
        "name": "Jane Miller",
        "age": 25,
        "email": "jane.miller@example.com",
        "jobTitle": "Content Writer",
        "experience": "3 years"
    }
]